sm_flask_oidc/__init__.py
sm_flask_oidc/sm_flask_oidc_helper.py
sm_flask_oidc-1.0.9.dist-info/LICENSE.txt
sm_flask_oidc-1.0.9.dist-info/METADATA
sm_flask_oidc-1.0.9.dist-info/WHEEL
sm_flask_oidc-1.0.9.dist-info/top_level.txt
sm_flask_oidc-1.0.9.dist-info/RECORD
